verilog/cpu/alu.v
module alu(
    in1,
    in2,
    carry,
    out
);

input  [3:0] in1, in2;
output [3:0] out;
output carry;

assign {carry, out} = in1 + in2;

endmodule

verilog/cpu/tb_alu.v
`include "alu.v"

module tb_alu();

reg  [3:0] in1, in2;
wire [3:0] out;
wire carry;

alu aluA (
    .in1 (in1),
    .in2 (in2),
    .out (out),
    .carry (carry)
);

initial begin
    $dumpfile("aluA.vcd");
    $dumpvars(0, aluA);
    $display("time\t in1 in2 out carry");
    $monitor("%g\t %b %b %b %b", $time, in1, in2, out, carry);
end

initial begin
    in1 = 4'b0000;
    in2 = 4'b0000;
    $display("expect :           0000, carry=0");
    #1 in1 = 4'b0001;
       in2 = 4'b0000;
    $display("expect :           0001, carry=0");
    #1 in1 = 4'b0010;
       in2 = 4'b0000;
    $display("expect :           0010, carry=0");
    #1 in1 = 4'b0010;
       in2 = 4'b0001;
    $display("expect :           0011, carry=0");
    #1 in1 = 4'b0010;
       in2 = 4'b0101;
    $display("expect :           0111, carry=0");
    #1 in1 = 4'b1010;
       in2 = 4'b0101;
    $display("expect :           1111, carry=0");
    #1 in1 = 4'b1011;
       in2 = 4'b0101;
    $display("expect :           0000, carry=1");
    #1 in1 = 4'b1011;
       in2 = 4'b0111;
    $display("expect :           0010, carry=1");
    #1 in1 = 4'b1111;
       in2 = 4'b0111;
    $display("expect :           0110, carry=1");
    #1 in1 = 4'b1111;
       in2 = 4'b1111;
    $display("expect :           1110, carry=1");
end


endmodule

verilog/cpu/aluA.vcd
$date
	Wed Feb 14 00:36:15 2018
$end
$version
	Icarus Verilog
$end
$timescale
	1s
$end
$scope module tb_alu $end
$scope module aluA $end
$var wire 4 ! in1 [3:0] $end
$var wire 4 " in2 [3:0] $end
$var wire 4 # out [3:0] $end
$var wire 1 $ carry $end
$upscope $end
$upscope $end
$enddefinitions $end
#0
$dumpvars
0$
b0 #
b0 "
b0 !
$end
#1
b1 #
b1 !
#2
b10 #
b10 !
#3
b11 #
b1 "
#4
b111 #
b101 "
#5
b1111 #
b1010 !
#6
b0 #
1$
b1011 !
#7
b10 #
b111 "
#8
b110 #
b1111 !
#9
b1110 #
b1111 "
