verilog/cpu/register.v
module register(clk, load, clr, in, out);

input clk, load, clr;
input  [3:0] in;
output [3:0] out;

wire clk, load, clr;
wire [3:0] in;
reg  [3:0] out;

reg [3:0] cache_in;

always @(posedge clk)
begin
    if (load == 1'b1) begin
        cache_in <= in;
        out <= in;
    end else begin
        out <= cache_in;
    end
end

endmodule

verilog/cpu/tb_register.v
`include "register.v"

// declare self
module tb_register();

reg clk, load, clr;
reg [3:0] in;
wire [3:0] out;


// instanticate register
register regA (
    // connect regA clk and testbench clk
    .clk  (clk),
    .load (load),
    .clr  (clr),
    .in   (in),
    .out  (out)
);


initial begin
    // ignore error
    $dumpfile("wave.vcd");
    $dumpvars(0, regA);
    $display ("time\t clock load clear in out");
    $monitor ("%g\t %b %b %b %b %b" , $time, clk, load, clr, in, out);
end

// clock generator
always begin
    #5 clk = ~clk;
end

initial begin
    clk = 1;
    load = 0;
    clr = 0;
    in = 4'b0;
    #10 load = 1;
    #0  in = 4'b1;       // 0001
    #10 in = in + 4'b1;  // 0010 , load=1, out=0010
    #10 load = 0;
    #0  in = in + 4'b1;  // 0011 , load=0, out=0010
    #10 in = in + 4'b1;  // 0100 , load=0, out=0010
    #10 load = 1;
    #0  in = in + 4'b1;  // 0101 , load=1, out=0101
    #10 in = in + 4'b1;  // 0110 , load=1, out=0110
    #10 in = in + 4'b1;  // 0111 , load=1, out=0111
    #10 $finish;
end

endmodule

verilog/cpu/wave.vcd
$date
	Sat Feb 10 00:33:30 2018
$end
$version
	Icarus Verilog
$end
$timescale
	1s
$end
$scope module tb_register $end
$scope module regA $end
$var wire 1 ! clk $end
$var wire 1 " clr $end
$var wire 4 # in [3:0] $end
$var wire 1 $ load $end
$var reg 4 % cache_in [3:0] $end
$var reg 4 & out [3:0] $end
$upscope $end
$upscope $end
$enddefinitions $end
#0
$dumpvars
bx &
bx %
0$
b0 #
0"
1!
$end
#5
0!
#10
b0 &
b0 %
b1 #
1!
1$
#15
0!
#20
b10 &
b10 %
1!
b10 #
#25
0!
#30
b11 #
1!
0$
#35
0!
#40
1!
b100 #
#45
0!
#50
b100 &
b100 %
b101 #
1!
1$
#55
0!
#60
b110 &
b110 %
1!
b110 #
#65
0!
#70
b111 &
b111 %
1!
b111 #
